princeton365/__init__.py
princeton365/_version.py
princeton365/board_generator.py
princeton365/evaluation.py
princeton365/generate_gt.py
princeton365/make_submission_public.py
princeton365/relative_pose.py
princeton365/upload_submission.py
princeton365/configs/board_configs.yaml
princeton365/optimization/__init__.py
princeton365/optimization/graph_optimization.py
princeton365/optimization/bundle_pnp/CMakeLists.txt
princeton365/optimization/bundle_pnp/board_experiment.cpp
princeton365/optimization/bundle_pnp/optimizer.cpp
princeton365/optimization/bundle_pnp/optimizer.h
princeton365/optimization/bundle_pnp/include/nlohmann/json.hpp
princeton365/optimization/rig_bundle_pnp/CMakeLists.txt
princeton365/optimization/rig_bundle_pnp/optimize_rig.cpp
princeton365/optimization/rig_bundle_pnp/include/cnpy.cpp
princeton365/optimization/rig_bundle_pnp/include/cnpy.h
princeton365/utils/__init__.py
princeton365/utils/gt_to_colmap.py
princeton365/utils/utils_aruco.py
princeton365/utils/utils_depth.py
princeton365/utils/utils_graph.py
princeton365/utils/utils_io.py
princeton365/utils/utils_trajectory.py
princeton365-0.3.1.dist-info/METADATA
princeton365-0.3.1.dist-info/WHEEL
princeton365-0.3.1.dist-info/entry_points.txt
princeton365-0.3.1.dist-info/licenses/LICENSE
princeton365-0.3.1.dist-info/RECORD
