Metadata-Version: 2.4
Name: princeton365
Version: 0.3.1
Summary: Princeton365: A Diverse Dataset with Accurate Camera Pose
Project-URL: Homepage, https://princeton365.cs.princeton.edu/
Project-URL: Repository, https://github.com/Princeton-VL/Princeton365
Project-URL: Paper, https://arxiv.org/abs/2506.09035
Maintainer-email: Karhan Kayan <kk2285@princeton.edu>, Stamatis Alexandropoulos <sa6924@princeton.edu>
License: BSD 3-Clause License
License-File: LICENSE
Provides-Extra: dev
Requires-Dist: evo; extra == 'dev'
Requires-Dist: filterpy; extra == 'dev'
Requires-Dist: g2o-python; extra == 'dev'
Requires-Dist: h5py; extra == 'dev'
Requires-Dist: matplotlib; extra == 'dev'
Requires-Dist: mplcursors; extra == 'dev'
Requires-Dist: networkx; extra == 'dev'
Requires-Dist: numpy; extra == 'dev'
Requires-Dist: oneeurofilter; extra == 'dev'
Requires-Dist: opencv-contrib-python; extra == 'dev'
Requires-Dist: pomegranate; extra == 'dev'
Requires-Dist: pyarrow; extra == 'dev'
Requires-Dist: pykalman; extra == 'dev'
Requires-Dist: pyqt5; extra == 'dev'
Requires-Dist: requests-toolbelt; extra == 'dev'
Requires-Dist: scipy; extra == 'dev'
Requires-Dist: tqdm; extra == 'dev'
